{
  "+79021889906": {
    "cookies": [
      {
        "comment": null,
        "comment_url": null,
        "discard": false,
        "domain": ".login.vk.com",
        "domain_initial_dot": false,
        "domain_specified": true,
        "expires": null,
        "name": "h",
        "path": "/",
        "path_specified": true,
        "port": null,
        "port_specified": false,
        "rest": {
          "HttpOnly": null
        },
        "rfc2109": false,
        "secure": false,
        "value": "1",
        "version": 0
      },
      {
        "comment": null,
        "comment_url": null,
        "discard": false,
        "domain": ".login.vk.com",
        "domain_initial_dot": false,
        "domain_specified": true,
        "expires": null,
        "name": "l",
        "path": "/",
        "path_specified": true,
        "port": null,
        "port_specified": false,
        "rest": {
          "HttpOnly": null
        },
        "rfc2109": false,
        "secure": true,
        "value": "361954932",
        "version": 0
      },
      {
        "comment": null,
        "comment_url": null,
        "discard": false,
        "domain": ".login.vk.com",
        "domain_initial_dot": false,
        "domain_specified": true,
        "expires": null,
        "name": "p",
        "path": "/",
        "path_specified": true,
        "port": null,
        "port_specified": false,
        "rest": {
          "HttpOnly": null
        },
        "rfc2109": false,
        "secure": true,
        "value": "2efc7b3baec7f38ba04e1887d277caada1788c08b5467fd9e99b3",
        "version": 0
      },
      {
        "comment": null,
        "comment_url": null,
        "discard": false,
        "domain": ".login.vk.com",
        "domain_initial_dot": false,
        "domain_specified": true,
        "expires": null,
        "name": "s",
        "path": "/",
        "path_specified": true,
        "port": null,
        "port_specified": false,
        "rest": {
          "HttpOnly": null
        },
        "rfc2109": false,
        "secure": true,
        "value": "1",
        "version": 0
      },
      {
        "comment": null,
        "comment_url": null,
        "discard": false,
        "domain": ".vk.com",
        "domain_initial_dot": true,
        "domain_specified": true,
        "expires": null,
        "name": "remixlang",
        "path": "/",
        "path_specified": true,
        "port": null,
        "port_specified": false,
        "rest": {},
        "rfc2109": false,
        "secure": false,
        "value": "3",
        "version": 0
      },
      {
        "comment": null,
        "comment_url": null,
        "discard": false,
        "domain": ".vk.com",
        "domain_initial_dot": true,
        "domain_specified": true,
        "expires": null,
        "name": "remixsid",
        "path": "/",
        "path_specified": true,
        "port": null,
        "port_specified": false,
        "rest": {},
        "rfc2109": false,
        "secure": true,
        "value": "59b7ed74bc4351f284091e3d50c0afc4525d34a05deeaf525d888",
        "version": 0
      },
      {
        "comment": null,
        "comment_url": null,
        "discard": false,
        "domain": ".vk.com",
        "domain_initial_dot": true,
        "domain_specified": true,
        "expires": null,
        "name": "remixstid",
        "path": "/",
        "path_specified": true,
        "port": null,
        "port_specified": false,
        "rest": {},
        "rfc2109": false,
        "secure": false,
        "value": "0_a4ebb2ebb6b918adc5",
        "version": 0
      },
      {
        "comment": null,
        "comment_url": null,
        "discard": false,
        "domain": ".vk.com",
        "domain_initial_dot": true,
        "domain_specified": true,
        "expires": null,
        "name": "remixusid",
        "path": "/",
        "path_specified": true,
        "port": null,
        "port_specified": false,
        "rest": {
          "HttpOnly": null
        },
        "rfc2109": false,
        "secure": true,
        "value": "ODk4ZTg2MjQwZTZiYWI4NWMwYzQ0ZWEy",
        "version": 0
      }
    ],
    "token": {
      "app6222115": {
        "scope_140492255": {
          "access_token": "a9aa59a5eeb4923fd93c22343f2654d684317a9092aab5b414d89d7661d71954e5e454bfb847858a25312",
          "expires_in": "0",
          "user_id": "361954932"
        }
      }
    }
  }
}